download_allccs.py
eval.py
hmdb2pkl.py
pred.py
pred_csv.py
preprocess.py
preprocess_oth.py
pretrain.py
qm92pkl.py
refmet2pkl.py
train.py
train_ccs.py
train_csv.py
train_rt.py
molnetpack/__init__.py
molnetpack/_version.py
molnetpack/dataset.py
molnetpack/model.py
molnetpack/molconv.py
molnetpack/molnet.py
molnetpack/utils.py
molnetpack/config/molnet.yml
molnetpack/config/molnet_ccs.yml
molnetpack/config/molnet_ccs_tl.yml
molnetpack/config/molnet_pre.yml
molnetpack/config/molnet_rt.yml
molnetpack/config/molnet_rt_tl.yml
molnetpack/config/preprocess_etkdgv3.yml
molnetpack/config/preprocess_hmdb.yml
molnetpack/data_utils/__init__.py
molnetpack/data_utils/all2mgf.py
molnetpack/data_utils/all2pkl.py
molnetpack/data_utils/filter.py
molnetpack/data_utils/utils.py
molnetpack-1.2.1.dist-info/licenses/LICENSE
molnetpack-1.2.1.dist-info/METADATA
molnetpack-1.2.1.dist-info/WHEEL
molnetpack-1.2.1.dist-info/top_level.txt
molnetpack-1.2.1.dist-info/RECORD
