Metadata-Version: 2.4
Name: molnetpack
Version: 1.2.1
Summary: 3DMolMS: prediction of tandem mass spectra from 3D molecular conformations
Author: Yuhui Hong, Sujun Li, Christopher J Welch, Shane Tichy, Yuzhen Ye, Haixu Tang
Maintainer-email: Yuhui Hong <yuhhong@iu.edu>
License: Attribution-NonCommercial-ShareAlike 4.0 International
Project-URL: Homepage, https://github.com/JosieHong/3DMolMS/
Project-URL: Issues, https://github.com/JosieHong/3DMolMS/issues
Project-URL: Changelog, https://github.com/JosieHong/3DMolMS/blob/main/CHANGE_LOG.md
Classifier: Programming Language :: Python :: 3
Classifier: Operating System :: OS Independent
Requires-Python: >=3.8
License-File: LICENSE
Requires-Dist: absl-py
Requires-Dist: beautifulsoup4
Requires-Dist: filelock
Requires-Dist: gdown
Requires-Dist: grpcio
Requires-Dist: importlib-metadata
Requires-Dist: lxml
Requires-Dist: markdown
Requires-Dist: markupsafe
Requires-Dist: molmass
Requires-Dist: numpy
Requires-Dist: pandas
Requires-Dist: protobuf
Requires-Dist: pysocks
Requires-Dist: pyteomics
Requires-Dist: soupsieve
Requires-Dist: tensorboard
Requires-Dist: PyYAML
Requires-Dist: rdkit
Requires-Dist: matplotlib
Requires-Dist: pillow
Dynamic: license-file
